LICENSE
setup.py
css_generate/__init__.py
css_generate/__main__.py
css_generate.egg-info/PKG-INFO
css_generate.egg-info/SOURCES.txt
css_generate.egg-info/dependency_links.txt
css_generate.egg-info/entry_points.txt
css_generate.egg-info/top_level.txt