Metadata-Version: 2.1
Name: css-generate
Version: 0.9943
Summary: Low-vision stylesheet generator
Home-page: https://ssb22.user.srcf.net/css
Author: Silas S. Brown
Author-email: ssb22@cam.ac.uk
License: Apache 2
Platform: any
Classifier: Programming Language :: Python :: 2
Classifier: Programming Language :: Python :: 3
Classifier: License :: OSI Approved :: Apache Software License
Classifier: Operating System :: OS Independent
Requires-Python: >=2.0
License-File: LICENSE
